bananopy/__init__.py
bananopy/banano.py
bananopy/constants.py
bananopy/conversion.py
bananopy/utils.py
bananopy-0.3.2.dist-info/LICENSE
bananopy-0.3.2.dist-info/WHEEL
bananopy-0.3.2.dist-info/METADATA
bananopy-0.3.2.dist-info/RECORD
