Metadata-Version: 2.1
Name: bananopy
Version: 0.3.2
Summary: Python library for interaction with Banano
Home-page: https://github.com/milkyklim/bananopy
License: MIT
Keywords: python,crypto,banano
Author: milkyklim
Author-email: 10698619+milkyklim@users.noreply.github.com
Requires-Python: >=3.7,<4.0
Classifier: License :: OSI Approved :: MIT License
Classifier: Programming Language :: Python :: 3
Classifier: Programming Language :: Python :: 3.7
Classifier: Programming Language :: Python :: 3.8
Requires-Dist: requests (>=2.23.0,<3.0.0)
Project-URL: Documentation, https://milkyklim.github.io/bananopy
Project-URL: Repository, https://github.com/milkyklim/bananopy
